{
  "id": "2461c968-167e-433f-a705-085ed2d02661",
  "prevId": "54874c35-9b83-460e-a587-7005c0d65ff2",
  "version": "7",
  "dialect": "postgresql",
  "tables": {
    "public.account": {
      "name": "account",
      "schema": "",
      "columns": {
        "userId": {
          "name": "userId",
          "type": "text",
          "primaryKey": false,
          "notNull": true
        },
        "type": {
          "name": "type",
          "type": "text",
          "primaryKey": false,
          "notNull": true
        },
        "provider": {
          "name": "provider",
          "type": "text",
          "primaryKey": false,
          "notNull": true
        },
        "providerAccountId": {
          "name": "providerAccountId",
          "type": "text",
          "primaryKey": false,
          "notNull": true
        },
        "refresh_token": {
          "name": "refresh_token",
          "type": "text",
          "primaryKey": false,
          "notNull": false
        },
        "access_token": {
          "name": "access_token",
          "type": "text",
          "primaryKey": false,
          "notNull": false
        },
        "expires_at": {
          "name": "expires_at",
          "type": "integer",
          "primaryKey": false,
          "notNull": false
        },
        "token_type": {
          "name": "token_type",
          "type": "text",
          "primaryKey": false,
          "notNull": false
        },
        "scope": {
          "name": "scope",
          "type": "text",
          "primaryKey": false,
          "notNull": false
        },
        "id_token": {
          "name": "id_token",
          "type": "text",
          "primaryKey": false,
          "notNull": false
        },
        "session_state": {
          "name": "session_state",
          "type": "text",
          "primaryKey": false,
          "notNull": false
        }
      },
      "indexes": {},
      "foreignKeys": {
        "account_userId_user_id_fk": {
          "name": "account_userId_user_id_fk",
          "tableFrom": "account",
          "tableTo": "user",
          "columnsFrom": [
            "userId"
          ],
          "columnsTo": [
            "id"
          ],
          "onDelete": "cascade",
          "onUpdate": "no action"
        }
      },
      "compositePrimaryKeys": {
        "account_provider_providerAccountId_pk": {
          "name": "account_provider_providerAccountId_pk",
          "columns": [
            "provider",
            "providerAccountId"
          ]
        }
      },
      "uniqueConstraints": {},
      "policies": {},
      "checkConstraints": {},
      "isRLSEnabled": false
    },
    "public.all_user": {
      "name": "all_user",
      "schema": "",
      "columns": {
        "id": {
          "name": "id",
          "type": "text",
          "primaryKey": true,
          "notNull": true
        },
        "type": {
          "name": "type",
          "type": "text",
          "primaryKey": false,
          "notNull": true
        },
        "user_id": {
          "name": "user_id",
          "type": "text",
          "primaryKey": false,
          "notNull": false
        },
        "temporary_user_id": {
          "name": "temporary_user_id",
          "type": "text",
          "primaryKey": false,
          "notNull": false
        },
        "created_at": {
          "name": "created_at",
          "type": "timestamp",
          "primaryKey": false,
          "notNull": true,
          "default": "now()"
        }
      },
      "indexes": {},
      "foreignKeys": {},
      "compositePrimaryKeys": {},
      "uniqueConstraints": {},
      "policies": {},
      "checkConstraints": {},
      "isRLSEnabled": false
    },
    "public.authenticator": {
      "name": "authenticator",
      "schema": "",
      "columns": {
        "credentialID": {
          "name": "credentialID",
          "type": "text",
          "primaryKey": false,
          "notNull": true
        },
        "userId": {
          "name": "userId",
          "type": "text",
          "primaryKey": false,
          "notNull": true
        },
        "providerAccountId": {
          "name": "providerAccountId",
          "type": "text",
          "primaryKey": false,
          "notNull": true
        },
        "credentialPublicKey": {
          "name": "credentialPublicKey",
          "type": "text",
          "primaryKey": false,
          "notNull": true
        },
        "counter": {
          "name": "counter",
          "type": "integer",
          "primaryKey": false,
          "notNull": true
        },
        "credentialDeviceType": {
          "name": "credentialDeviceType",
          "type": "text",
          "primaryKey": false,
          "notNull": true
        },
        "credentialBackedUp": {
          "name": "credentialBackedUp",
          "type": "boolean",
          "primaryKey": false,
          "notNull": true
        },
        "transports": {
          "name": "transports",
          "type": "text",
          "primaryKey": false,
          "notNull": false
        }
      },
      "indexes": {},
      "foreignKeys": {
        "authenticator_userId_user_id_fk": {
          "name": "authenticator_userId_user_id_fk",
          "tableFrom": "authenticator",
          "tableTo": "user",
          "columnsFrom": [
            "userId"
          ],
          "columnsTo": [
            "id"
          ],
          "onDelete": "cascade",
          "onUpdate": "no action"
        }
      },
      "compositePrimaryKeys": {},
      "uniqueConstraints": {
        "authenticator_credentialID_unique": {
          "name": "authenticator_credentialID_unique",
          "nullsNotDistinct": false,
          "columns": [
            "credentialID"
          ]
        }
      },
      "policies": {},
      "checkConstraints": {},
      "isRLSEnabled": false
    },
    "public.document": {
      "name": "document",
      "schema": "",
      "columns": {
        "id": {
          "name": "id",
          "type": "text",
          "primaryKey": true,
          "notNull": true
        },
        "owner_id": {
          "name": "owner_id",
          "type": "text",
          "primaryKey": false,
          "notNull": true
        },
        "url": {
          "name": "url",
          "type": "text",
          "primaryKey": false,
          "notNull": true
        },
        "title": {
          "name": "title",
          "type": "text",
          "primaryKey": false,
          "notNull": false
        },
        "description": {
          "name": "description",
          "type": "text",
          "primaryKey": false,
          "notNull": false
        },
        "mime_type": {
          "name": "mime_type",
          "type": "text",
          "primaryKey": false,
          "notNull": true
        },
        "size": {
          "name": "size",
          "type": "text",
          "primaryKey": false,
          "notNull": true
        },
        "created_at": {
          "name": "created_at",
          "type": "timestamp",
          "primaryKey": false,
          "notNull": true,
          "default": "now()"
        },
        "is_public": {
          "name": "is_public",
          "type": "boolean",
          "primaryKey": false,
          "notNull": false,
          "default": false
        },
        "owner_secure_code": {
          "name": "owner_secure_code",
          "type": "text",
          "primaryKey": false,
          "notNull": true
        },
        "metadata": {
          "name": "metadata",
          "type": "json",
          "primaryKey": false,
          "notNull": false,
          "default": "'{\"size\":0,\"mimeType\":\"\",\"originalName\":\"\",\"uploadedAt\":\"2025-04-01T14:18:17.246Z\"}'::json"
        }
      },
      "indexes": {},
      "foreignKeys": {
        "document_owner_id_all_user_id_fk": {
          "name": "document_owner_id_all_user_id_fk",
          "tableFrom": "document",
          "tableTo": "all_user",
          "columnsFrom": [
            "owner_id"
          ],
          "columnsTo": [
            "id"
          ],
          "onDelete": "cascade",
          "onUpdate": "no action"
        }
      },
      "compositePrimaryKeys": {},
      "uniqueConstraints": {},
      "policies": {},
      "checkConstraints": {},
      "isRLSEnabled": false
    },
    "public.family_member": {
      "name": "family_member",
      "schema": "",
      "columns": {
        "id": {
          "name": "id",
          "type": "text",
          "primaryKey": true,
          "notNull": true
        },
        "owner_id": {
          "name": "owner_id",
          "type": "text",
          "primaryKey": false,
          "notNull": true
        },
        "user_id": {
          "name": "user_id",
          "type": "text",
          "primaryKey": false,
          "notNull": false
        },
        "full_name": {
          "name": "full_name",
          "type": "text",
          "primaryKey": false,
          "notNull": true
        },
        "primary_relationship": {
          "name": "primary_relationship",
          "type": "text",
          "primaryKey": false,
          "notNull": true
        },
        "fuzzy_relationships": {
          "name": "fuzzy_relationships",
          "type": "text[]",
          "primaryKey": false,
          "notNull": true,
          "default": "'{}'"
        },
        "birth_date": {
          "name": "birth_date",
          "type": "timestamp",
          "primaryKey": false,
          "notNull": false
        },
        "death_date": {
          "name": "death_date",
          "type": "timestamp",
          "primaryKey": false,
          "notNull": false
        },
        "birthplace": {
          "name": "birthplace",
          "type": "text",
          "primaryKey": false,
          "notNull": false
        },
        "metadata": {
          "name": "metadata",
          "type": "json",
          "primaryKey": false,
          "notNull": false,
          "default": "'{}'::json"
        },
        "created_at": {
          "name": "created_at",
          "type": "timestamp",
          "primaryKey": false,
          "notNull": true,
          "default": "now()"
        }
      },
      "indexes": {},
      "foreignKeys": {
        "family_member_owner_id_all_user_id_fk": {
          "name": "family_member_owner_id_all_user_id_fk",
          "tableFrom": "family_member",
          "tableTo": "all_user",
          "columnsFrom": [
            "owner_id"
          ],
          "columnsTo": [
            "id"
          ],
          "onDelete": "cascade",
          "onUpdate": "no action"
        },
        "family_member_user_id_all_user_id_fk": {
          "name": "family_member_user_id_all_user_id_fk",
          "tableFrom": "family_member",
          "tableTo": "all_user",
          "columnsFrom": [
            "user_id"
          ],
          "columnsTo": [
            "id"
          ],
          "onDelete": "set null",
          "onUpdate": "no action"
        },
        "family_member_user_fk": {
          "name": "family_member_user_fk",
          "tableFrom": "family_member",
          "tableTo": "all_user",
          "columnsFrom": [
            "user_id"
          ],
          "columnsTo": [
            "id"
          ],
          "onDelete": "no action",
          "onUpdate": "no action"
        }
      },
      "compositePrimaryKeys": {},
      "uniqueConstraints": {},
      "policies": {},
      "checkConstraints": {},
      "isRLSEnabled": false
    },
    "public.family_relationship": {
      "name": "family_relationship",
      "schema": "",
      "columns": {
        "id": {
          "name": "id",
          "type": "text",
          "primaryKey": true,
          "notNull": true
        },
        "relationship_id": {
          "name": "relationship_id",
          "type": "text",
          "primaryKey": false,
          "notNull": true
        },
        "family_role": {
          "name": "family_role",
          "type": "text",
          "primaryKey": false,
          "notNull": true
        },
        "relationship_clarity": {
          "name": "relationship_clarity",
          "type": "text",
          "primaryKey": false,
          "notNull": true,
          "default": "'fuzzy'"
        },
        "shared_ancestor_id": {
          "name": "shared_ancestor_id",
          "type": "text",
          "primaryKey": false,
          "notNull": false
        },
        "created_at": {
          "name": "created_at",
          "type": "timestamp",
          "primaryKey": false,
          "notNull": true,
          "default": "now()"
        }
      },
      "indexes": {},
      "foreignKeys": {
        "family_relationship_relationship_id_relationship_id_fk": {
          "name": "family_relationship_relationship_id_relationship_id_fk",
          "tableFrom": "family_relationship",
          "tableTo": "relationship",
          "columnsFrom": [
            "relationship_id"
          ],
          "columnsTo": [
            "id"
          ],
          "onDelete": "cascade",
          "onUpdate": "no action"
        },
        "family_relationship_shared_ancestor_id_all_user_id_fk": {
          "name": "family_relationship_shared_ancestor_id_all_user_id_fk",
          "tableFrom": "family_relationship",
          "tableTo": "all_user",
          "columnsFrom": [
            "shared_ancestor_id"
          ],
          "columnsTo": [
            "id"
          ],
          "onDelete": "set null",
          "onUpdate": "no action"
        }
      },
      "compositePrimaryKeys": {},
      "uniqueConstraints": {},
      "policies": {},
      "checkConstraints": {},
      "isRLSEnabled": false
    },
    "public.group": {
      "name": "group",
      "schema": "",
      "columns": {
        "id": {
          "name": "id",
          "type": "text",
          "primaryKey": true,
          "notNull": true
        },
        "name": {
          "name": "name",
          "type": "text",
          "primaryKey": false,
          "notNull": true
        },
        "owner_id": {
          "name": "owner_id",
          "type": "text",
          "primaryKey": false,
          "notNull": true
        },
        "created_at": {
          "name": "created_at",
          "type": "timestamp",
          "primaryKey": false,
          "notNull": true,
          "default": "now()"
        },
        "metadata": {
          "name": "metadata",
          "type": "json",
          "primaryKey": false,
          "notNull": false,
          "default": "'{}'::json"
        }
      },
      "indexes": {},
      "foreignKeys": {
        "group_owner_id_user_id_fk": {
          "name": "group_owner_id_user_id_fk",
          "tableFrom": "group",
          "tableTo": "user",
          "columnsFrom": [
            "owner_id"
          ],
          "columnsTo": [
            "id"
          ],
          "onDelete": "cascade",
          "onUpdate": "no action"
        }
      },
      "compositePrimaryKeys": {},
      "uniqueConstraints": {},
      "policies": {},
      "checkConstraints": {},
      "isRLSEnabled": false
    },
    "public.group_member": {
      "name": "group_member",
      "schema": "",
      "columns": {
        "group_id": {
          "name": "group_id",
          "type": "text",
          "primaryKey": false,
          "notNull": true
        },
        "user_id": {
          "name": "user_id",
          "type": "text",
          "primaryKey": false,
          "notNull": true
        },
        "role": {
          "name": "role",
          "type": "text",
          "primaryKey": false,
          "notNull": true,
          "default": "'member'"
        }
      },
      "indexes": {},
      "foreignKeys": {
        "group_member_group_id_group_id_fk": {
          "name": "group_member_group_id_group_id_fk",
          "tableFrom": "group_member",
          "tableTo": "group",
          "columnsFrom": [
            "group_id"
          ],
          "columnsTo": [
            "id"
          ],
          "onDelete": "cascade",
          "onUpdate": "no action"
        },
        "group_member_user_id_user_id_fk": {
          "name": "group_member_user_id_user_id_fk",
          "tableFrom": "group_member",
          "tableTo": "user",
          "columnsFrom": [
            "user_id"
          ],
          "columnsTo": [
            "id"
          ],
          "onDelete": "cascade",
          "onUpdate": "no action"
        }
      },
      "compositePrimaryKeys": {
        "group_member_group_id_user_id_pk": {
          "name": "group_member_group_id_user_id_pk",
          "columns": [
            "group_id",
            "user_id"
          ]
        }
      },
      "uniqueConstraints": {},
      "policies": {},
      "checkConstraints": {},
      "isRLSEnabled": false
    },
    "public.image": {
      "name": "image",
      "schema": "",
      "columns": {
        "id": {
          "name": "id",
          "type": "text",
          "primaryKey": true,
          "notNull": true
        },
        "owner_id": {
          "name": "owner_id",
          "type": "text",
          "primaryKey": false,
          "notNull": true
        },
        "url": {
          "name": "url",
          "type": "text",
          "primaryKey": false,
          "notNull": true
        },
        "caption": {
          "name": "caption",
          "type": "text",
          "primaryKey": false,
          "notNull": false
        },
        "created_at": {
          "name": "created_at",
          "type": "timestamp",
          "primaryKey": false,
          "notNull": true,
          "default": "now()"
        },
        "is_public": {
          "name": "is_public",
          "type": "boolean",
          "primaryKey": false,
          "notNull": false,
          "default": false
        },
        "title": {
          "name": "title",
          "type": "text",
          "primaryKey": false,
          "notNull": false
        },
        "description": {
          "name": "description",
          "type": "text",
          "primaryKey": false,
          "notNull": false
        },
        "owner_secure_code": {
          "name": "owner_secure_code",
          "type": "text",
          "primaryKey": false,
          "notNull": true
        },
        "metadata": {
          "name": "metadata",
          "type": "json",
          "primaryKey": false,
          "notNull": false,
          "default": "'{\"size\":0,\"mimeType\":\"\",\"originalName\":\"\",\"uploadedAt\":\"2025-04-01T14:18:17.245Z\"}'::json"
        }
      },
      "indexes": {},
      "foreignKeys": {
        "image_owner_id_all_user_id_fk": {
          "name": "image_owner_id_all_user_id_fk",
          "tableFrom": "image",
          "tableTo": "all_user",
          "columnsFrom": [
            "owner_id"
          ],
          "columnsTo": [
            "id"
          ],
          "onDelete": "cascade",
          "onUpdate": "no action"
        }
      },
      "compositePrimaryKeys": {},
      "uniqueConstraints": {},
      "policies": {},
      "checkConstraints": {},
      "isRLSEnabled": false
    },
    "public.memory_share": {
      "name": "memory_share",
      "schema": "",
      "columns": {
        "id": {
          "name": "id",
          "type": "text",
          "primaryKey": true,
          "notNull": true
        },
        "memory_id": {
          "name": "memory_id",
          "type": "text",
          "primaryKey": false,
          "notNull": true
        },
        "memory_type": {
          "name": "memory_type",
          "type": "text",
          "primaryKey": false,
          "notNull": true
        },
        "owner_id": {
          "name": "owner_id",
          "type": "text",
          "primaryKey": false,
          "notNull": true
        },
        "shared_with_type": {
          "name": "shared_with_type",
          "type": "text",
          "primaryKey": false,
          "notNull": true
        },
        "shared_with_id": {
          "name": "shared_with_id",
          "type": "text",
          "primaryKey": false,
          "notNull": false
        },
        "group_id": {
          "name": "group_id",
          "type": "text",
          "primaryKey": false,
          "notNull": false
        },
        "shared_relationship_type": {
          "name": "shared_relationship_type",
          "type": "text",
          "primaryKey": false,
          "notNull": false
        },
        "access_level": {
          "name": "access_level",
          "type": "text",
          "primaryKey": false,
          "notNull": true,
          "default": "'read'"
        },
        "invitee_secure_code": {
          "name": "invitee_secure_code",
          "type": "text",
          "primaryKey": false,
          "notNull": true
        },
        "secure_code_created_at": {
          "name": "secure_code_created_at",
          "type": "timestamp",
          "primaryKey": false,
          "notNull": true,
          "default": "now()"
        },
        "created_at": {
          "name": "created_at",
          "type": "timestamp",
          "primaryKey": false,
          "notNull": true,
          "default": "now()"
        }
      },
      "indexes": {},
      "foreignKeys": {
        "memory_share_owner_id_all_user_id_fk": {
          "name": "memory_share_owner_id_all_user_id_fk",
          "tableFrom": "memory_share",
          "tableTo": "all_user",
          "columnsFrom": [
            "owner_id"
          ],
          "columnsTo": [
            "id"
          ],
          "onDelete": "cascade",
          "onUpdate": "no action"
        },
        "memory_share_shared_with_id_all_user_id_fk": {
          "name": "memory_share_shared_with_id_all_user_id_fk",
          "tableFrom": "memory_share",
          "tableTo": "all_user",
          "columnsFrom": [
            "shared_with_id"
          ],
          "columnsTo": [
            "id"
          ],
          "onDelete": "cascade",
          "onUpdate": "no action"
        },
        "memory_share_group_id_group_id_fk": {
          "name": "memory_share_group_id_group_id_fk",
          "tableFrom": "memory_share",
          "tableTo": "group",
          "columnsFrom": [
            "group_id"
          ],
          "columnsTo": [
            "id"
          ],
          "onDelete": "cascade",
          "onUpdate": "no action"
        }
      },
      "compositePrimaryKeys": {},
      "uniqueConstraints": {},
      "policies": {},
      "checkConstraints": {},
      "isRLSEnabled": false
    },
    "public.note": {
      "name": "note",
      "schema": "",
      "columns": {
        "id": {
          "name": "id",
          "type": "text",
          "primaryKey": true,
          "notNull": true
        },
        "owner_id": {
          "name": "owner_id",
          "type": "text",
          "primaryKey": false,
          "notNull": true
        },
        "title": {
          "name": "title",
          "type": "text",
          "primaryKey": false,
          "notNull": true
        },
        "content": {
          "name": "content",
          "type": "text",
          "primaryKey": false,
          "notNull": true
        },
        "created_at": {
          "name": "created_at",
          "type": "timestamp",
          "primaryKey": false,
          "notNull": true,
          "default": "now()"
        },
        "updated_at": {
          "name": "updated_at",
          "type": "timestamp",
          "primaryKey": false,
          "notNull": true,
          "default": "now()"
        },
        "is_public": {
          "name": "is_public",
          "type": "boolean",
          "primaryKey": false,
          "notNull": false,
          "default": false
        },
        "owner_secure_code": {
          "name": "owner_secure_code",
          "type": "text",
          "primaryKey": false,
          "notNull": true
        },
        "metadata": {
          "name": "metadata",
          "type": "json",
          "primaryKey": false,
          "notNull": false,
          "default": "'{}'::json"
        }
      },
      "indexes": {},
      "foreignKeys": {
        "note_owner_id_all_user_id_fk": {
          "name": "note_owner_id_all_user_id_fk",
          "tableFrom": "note",
          "tableTo": "all_user",
          "columnsFrom": [
            "owner_id"
          ],
          "columnsTo": [
            "id"
          ],
          "onDelete": "cascade",
          "onUpdate": "no action"
        }
      },
      "compositePrimaryKeys": {},
      "uniqueConstraints": {},
      "policies": {},
      "checkConstraints": {},
      "isRLSEnabled": false
    },
    "public.relationship": {
      "name": "relationship",
      "schema": "",
      "columns": {
        "id": {
          "name": "id",
          "type": "text",
          "primaryKey": true,
          "notNull": true
        },
        "user_id": {
          "name": "user_id",
          "type": "text",
          "primaryKey": false,
          "notNull": true
        },
        "related_user_id": {
          "name": "related_user_id",
          "type": "text",
          "primaryKey": false,
          "notNull": true
        },
        "type": {
          "name": "type",
          "type": "text",
          "primaryKey": false,
          "notNull": true
        },
        "status": {
          "name": "status",
          "type": "text",
          "primaryKey": false,
          "notNull": true,
          "default": "'pending'"
        },
        "note": {
          "name": "note",
          "type": "text",
          "primaryKey": false,
          "notNull": false
        },
        "created_at": {
          "name": "created_at",
          "type": "timestamp",
          "primaryKey": false,
          "notNull": true,
          "default": "now()"
        }
      },
      "indexes": {
        "unique_relation_idx": {
          "name": "unique_relation_idx",
          "columns": [
            {
              "expression": "user_id",
              "isExpression": false,
              "asc": true,
              "nulls": "last"
            },
            {
              "expression": "related_user_id",
              "isExpression": false,
              "asc": true,
              "nulls": "last"
            }
          ],
          "isUnique": true,
          "concurrently": false,
          "method": "btree",
          "with": {}
        }
      },
      "foreignKeys": {
        "relationship_user_id_all_user_id_fk": {
          "name": "relationship_user_id_all_user_id_fk",
          "tableFrom": "relationship",
          "tableTo": "all_user",
          "columnsFrom": [
            "user_id"
          ],
          "columnsTo": [
            "id"
          ],
          "onDelete": "cascade",
          "onUpdate": "no action"
        },
        "relationship_related_user_id_all_user_id_fk": {
          "name": "relationship_related_user_id_all_user_id_fk",
          "tableFrom": "relationship",
          "tableTo": "all_user",
          "columnsFrom": [
            "related_user_id"
          ],
          "columnsTo": [
            "id"
          ],
          "onDelete": "cascade",
          "onUpdate": "no action"
        }
      },
      "compositePrimaryKeys": {},
      "uniqueConstraints": {},
      "policies": {},
      "checkConstraints": {},
      "isRLSEnabled": false
    },
    "public.session": {
      "name": "session",
      "schema": "",
      "columns": {
        "sessionToken": {
          "name": "sessionToken",
          "type": "text",
          "primaryKey": true,
          "notNull": true
        },
        "userId": {
          "name": "userId",
          "type": "text",
          "primaryKey": false,
          "notNull": true
        },
        "expires": {
          "name": "expires",
          "type": "timestamp",
          "primaryKey": false,
          "notNull": true
        }
      },
      "indexes": {},
      "foreignKeys": {
        "session_userId_user_id_fk": {
          "name": "session_userId_user_id_fk",
          "tableFrom": "session",
          "tableTo": "user",
          "columnsFrom": [
            "userId"
          ],
          "columnsTo": [
            "id"
          ],
          "onDelete": "cascade",
          "onUpdate": "no action"
        }
      },
      "compositePrimaryKeys": {},
      "uniqueConstraints": {},
      "policies": {},
      "checkConstraints": {},
      "isRLSEnabled": false
    },
    "public.temporary_user": {
      "name": "temporary_user",
      "schema": "",
      "columns": {
        "id": {
          "name": "id",
          "type": "text",
          "primaryKey": true,
          "notNull": true
        },
        "name": {
          "name": "name",
          "type": "text",
          "primaryKey": false,
          "notNull": false
        },
        "email": {
          "name": "email",
          "type": "text",
          "primaryKey": false,
          "notNull": false
        },
        "secure_code": {
          "name": "secure_code",
          "type": "text",
          "primaryKey": false,
          "notNull": true
        },
        "secure_code_expires_at": {
          "name": "secure_code_expires_at",
          "type": "timestamp",
          "primaryKey": false,
          "notNull": true
        },
        "role": {
          "name": "role",
          "type": "text",
          "primaryKey": false,
          "notNull": true
        },
        "invited_by_all_user_id": {
          "name": "invited_by_all_user_id",
          "type": "text",
          "primaryKey": false,
          "notNull": false
        },
        "registration_status": {
          "name": "registration_status",
          "type": "text",
          "primaryKey": false,
          "notNull": true,
          "default": "'pending'"
        },
        "created_at": {
          "name": "created_at",
          "type": "timestamp",
          "primaryKey": false,
          "notNull": true,
          "default": "now()"
        },
        "updated_at": {
          "name": "updated_at",
          "type": "timestamp",
          "primaryKey": false,
          "notNull": true,
          "default": "now()"
        },
        "metadata": {
          "name": "metadata",
          "type": "json",
          "primaryKey": false,
          "notNull": false,
          "default": "'{}'::json"
        }
      },
      "indexes": {},
      "foreignKeys": {
        "temporary_user_invited_by_fk": {
          "name": "temporary_user_invited_by_fk",
          "tableFrom": "temporary_user",
          "tableTo": "all_user",
          "columnsFrom": [
            "invited_by_all_user_id"
          ],
          "columnsTo": [
            "id"
          ],
          "onDelete": "no action",
          "onUpdate": "no action"
        }
      },
      "compositePrimaryKeys": {},
      "uniqueConstraints": {},
      "policies": {},
      "checkConstraints": {},
      "isRLSEnabled": false
    },
    "public.user": {
      "name": "user",
      "schema": "",
      "columns": {
        "id": {
          "name": "id",
          "type": "text",
          "primaryKey": true,
          "notNull": true
        },
        "name": {
          "name": "name",
          "type": "text",
          "primaryKey": false,
          "notNull": false
        },
        "email": {
          "name": "email",
          "type": "text",
          "primaryKey": false,
          "notNull": false
        },
        "emailVerified": {
          "name": "emailVerified",
          "type": "timestamp",
          "primaryKey": false,
          "notNull": false
        },
        "image": {
          "name": "image",
          "type": "text",
          "primaryKey": false,
          "notNull": false
        },
        "password": {
          "name": "password",
          "type": "text",
          "primaryKey": false,
          "notNull": false
        },
        "username": {
          "name": "username",
          "type": "text",
          "primaryKey": false,
          "notNull": false
        },
        "parent_id": {
          "name": "parent_id",
          "type": "text",
          "primaryKey": false,
          "notNull": false
        },
        "invited_by_all_user_id": {
          "name": "invited_by_all_user_id",
          "type": "text",
          "primaryKey": false,
          "notNull": false
        },
        "invited_at": {
          "name": "invited_at",
          "type": "timestamp",
          "primaryKey": false,
          "notNull": false
        },
        "registration_status": {
          "name": "registration_status",
          "type": "text",
          "primaryKey": false,
          "notNull": true,
          "default": "'pending'"
        },
        "role": {
          "name": "role",
          "type": "text",
          "primaryKey": false,
          "notNull": true,
          "default": "'user'"
        },
        "plan": {
          "name": "plan",
          "type": "text",
          "primaryKey": false,
          "notNull": true,
          "default": "'free'"
        },
        "premium_expires_at": {
          "name": "premium_expires_at",
          "type": "timestamp",
          "primaryKey": false,
          "notNull": false
        },
        "created_at": {
          "name": "created_at",
          "type": "timestamp",
          "primaryKey": false,
          "notNull": true,
          "default": "now()"
        },
        "updated_at": {
          "name": "updated_at",
          "type": "timestamp",
          "primaryKey": false,
          "notNull": true,
          "default": "now()"
        },
        "metadata": {
          "name": "metadata",
          "type": "json",
          "primaryKey": false,
          "notNull": false,
          "default": "'{}'::json"
        }
      },
      "indexes": {},
      "foreignKeys": {
        "user_invited_by_fk": {
          "name": "user_invited_by_fk",
          "tableFrom": "user",
          "tableTo": "user",
          "columnsFrom": [
            "invited_by_all_user_id"
          ],
          "columnsTo": [
            "id"
          ],
          "onDelete": "no action",
          "onUpdate": "no action"
        },
        "user_parent_fk": {
          "name": "user_parent_fk",
          "tableFrom": "user",
          "tableTo": "user",
          "columnsFrom": [
            "parent_id"
          ],
          "columnsTo": [
            "id"
          ],
          "onDelete": "no action",
          "onUpdate": "no action"
        }
      },
      "compositePrimaryKeys": {},
      "uniqueConstraints": {
        "user_email_unique": {
          "name": "user_email_unique",
          "nullsNotDistinct": false,
          "columns": [
            "email"
          ]
        },
        "user_username_unique": {
          "name": "user_username_unique",
          "nullsNotDistinct": false,
          "columns": [
            "username"
          ]
        }
      },
      "policies": {},
      "checkConstraints": {},
      "isRLSEnabled": false
    },
    "public.verificationToken": {
      "name": "verificationToken",
      "schema": "",
      "columns": {
        "identifier": {
          "name": "identifier",
          "type": "text",
          "primaryKey": false,
          "notNull": true
        },
        "token": {
          "name": "token",
          "type": "text",
          "primaryKey": false,
          "notNull": true
        },
        "expires": {
          "name": "expires",
          "type": "timestamp",
          "primaryKey": false,
          "notNull": true
        }
      },
      "indexes": {},
      "foreignKeys": {},
      "compositePrimaryKeys": {
        "verificationToken_identifier_token_pk": {
          "name": "verificationToken_identifier_token_pk",
          "columns": [
            "identifier",
            "token"
          ]
        }
      },
      "uniqueConstraints": {},
      "policies": {},
      "checkConstraints": {},
      "isRLSEnabled": false
    },
    "public.video": {
      "name": "video",
      "schema": "",
      "columns": {
        "id": {
          "name": "id",
          "type": "text",
          "primaryKey": true,
          "notNull": true
        },
        "owner_id": {
          "name": "owner_id",
          "type": "text",
          "primaryKey": false,
          "notNull": true
        },
        "url": {
          "name": "url",
          "type": "text",
          "primaryKey": false,
          "notNull": true
        },
        "title": {
          "name": "title",
          "type": "text",
          "primaryKey": false,
          "notNull": true
        },
        "description": {
          "name": "description",
          "type": "text",
          "primaryKey": false,
          "notNull": false
        },
        "duration": {
          "name": "duration",
          "type": "integer",
          "primaryKey": false,
          "notNull": false
        },
        "mime_type": {
          "name": "mime_type",
          "type": "text",
          "primaryKey": false,
          "notNull": true
        },
        "size": {
          "name": "size",
          "type": "text",
          "primaryKey": false,
          "notNull": true
        },
        "owner_secure_code": {
          "name": "owner_secure_code",
          "type": "text",
          "primaryKey": false,
          "notNull": true
        },
        "created_at": {
          "name": "created_at",
          "type": "timestamp",
          "primaryKey": false,
          "notNull": true,
          "default": "now()"
        },
        "updated_at": {
          "name": "updated_at",
          "type": "timestamp",
          "primaryKey": false,
          "notNull": true,
          "default": "now()"
        },
        "metadata": {
          "name": "metadata",
          "type": "json",
          "primaryKey": false,
          "notNull": false,
          "default": "'{}'::json"
        }
      },
      "indexes": {},
      "foreignKeys": {
        "video_owner_id_all_user_id_fk": {
          "name": "video_owner_id_all_user_id_fk",
          "tableFrom": "video",
          "tableTo": "all_user",
          "columnsFrom": [
            "owner_id"
          ],
          "columnsTo": [
            "id"
          ],
          "onDelete": "cascade",
          "onUpdate": "no action"
        }
      },
      "compositePrimaryKeys": {},
      "uniqueConstraints": {},
      "policies": {},
      "checkConstraints": {},
      "isRLSEnabled": false
    }
  },
  "enums": {},
  "schemas": {},
  "sequences": {},
  "roles": {},
  "policies": {},
  "views": {},
  "_meta": {
    "columns": {},
    "schemas": {},
    "tables": {}
  }
}